[
  {
    "meta": {
      "name": "Systems_Architecture_MAX",
      "kernel_source": "Technology_Architecture_Principles",
      "version": "1.0.0",
      "created_utc": "2025-04-21T10:00:00.000000Z",
      "density_profile": "kernel_x100k_virtual",
      "description": "MAX-density systems architecture kernel integrating distributed systems, microservices, and deterministic infrastructure."
    },
    "kernel": {
      "kernel_name": "Systems_Architecture_ULTRA_Kernel",
      "version": "1.0",
      "scope": "Cross-domain technology architecture integrating distributed systems, reliability engineering, and deterministic computing.",
      "domains": {
        "distributed_systems": {
          "principles": [
            "consistency_models",
            "partition_tolerance",
            "fault_tolerance",
            "scalability_patterns"
          ],
          "rules": [
            "DIST_RULE_1: CAP theorem: choose 2 of Consistency, Availability, Partition-tolerance.",
            "DIST_RULE_2: Eventual consistency acceptable for many distributed use cases.",
            "DIST_RULE_3: Fault tolerance requires redundancy and graceful degradation.",
            "DIST_RULE_4: Horizontal scaling preferred over vertical scaling."
          ]
        },
        "reliability_engineering": {
          "principles": [
            "circuit_breakers",
            "retry_patterns",
            "observability",
            "chaos_engineering"
          ],
          "rules": [
            "REL_RULE_1: Circuit breakers prevent cascade failures.",
            "REL_RULE_2: Exponential backoff with jitter for retries.",
            "REL_RULE_3: Full observability: metrics, logs, traces.",
            "REL_RULE_4: Chaos engineering validates failure handling."
          ]
        },
        "security_architecture": {
          "principles": [
            "defense_in_depth",
            "least_privilege",
            "zero_trust",
            "audit_logging"
          ],
          "rules": [
            "SEC_RULE_1: Defense in depth with multiple security layers.",
            "SEC_RULE_2: Principle of least privilege for all access.",
            "SEC_RULE_3: Zero trust: verify every request regardless of origin.",
            "SEC_RULE_4: Complete audit logging for all security events."
          ]
        }
      },
      "equations": [
        "Availability = MTBF / (MTBF + MTTR)",
        "Error Budget = 1 - SLO Target",
        "Latency_percentile = max(response_times[:p%])",
        "Throughput = Requests / Time"
      ],
      "invariants": [
        "INV_TECH_1: All state changes must be auditable and reversible.",
        "INV_TECH_2: System must degrade gracefully under load.",
        "INV_TECH_3: No single point of failure in critical paths."
      ],
      "references": [
        "Brewer, E. (2000). Towards Robust Distributed Systems.",
        "Vogels, W. (2009). Eventually Consistent.",
        "Nygard, M.T. (2007). Release It! Design and Deploy Production-Ready Software."
      ]
    }
  }
]
