{
  "meta": {
    "name": "AMOS_Chinese_Legal_System_Kernel_Engine_vInfinity_SUPER",
    "version": "v1.0.0",
    "author": "Trang Phan",
    "type": "Kernel_Engine_Composite",
    "language": "English",
    "description": "Deterministic kernel+engine for structurally modeling Chinese law and regulations across all domains (civil, commercial, administrative, criminal, tax, IP, data, labour, environment, finance, etc.). Conceptual only; not legal advice.",
    "created_at_utc": "2025-11-28T09:38:41.297746Z",
    "density_profile": "kernel_x100k_virtual"
  },
  "scope": {
    "legal_domains": [
      "constitutional_and_state_structure",
      "civil_and_contract",
      "company_and_corporate_governance",
      "securities_and_capital_markets",
      "banking_and_finance",
      "competition_and_antitrust",
      "consumer_protection",
      "intellectual_property",
      "data_and_cybersecurity",
      "labour_and_employment",
      "social_security",
      "environment_and_resource",
      "taxation",
      "administrative_law_and_procedure",
      "criminal_law_and_procedure",
      "procedural_law_civil",
      "procedural_law_administrative",
      "procedural_law_criminal",
      "foreign_investment_and_trade",
      "maritime_and_transport",
      "family_and_inheritance"
    ],
    "instrument_types": [
      "constitution_and_basic_law",
      "national_statute",
      "national_standing_committee_interpretation",
      "administrative_regulation_state_council",
      "judicial_interpretation_supreme_court",
      "judicial_interpretation_supreme_procuratorate",
      "local_regulation_provincial",
      "local_regulation_municipal",
      "departmental_rule_ministry_commission",
      "normative_document_guidance",
      "treaty_and_international_agreement",
      "judicial_guiding_case",
      "arbitration_rule"
    ],
    "integration_refs": [
      "Policy_Geostrategy_Kernel_vInfinity_SUPER",
      "Risk_Compliance_Kernel_vInfinity_SUPER",
      "BizFin_Kernel_vInfinity",
      "AMOS_C09_org_law_policy",
      "AMOS_BRAIN_SUPER_with_C_CANON",
      "AMOS_C_CANON_SUPER_CLEAN_x100k"
    ],
    "disclaimer": "This structure is conceptual and educational. It does not provide legal advice, official interpretations, or live statute/case content."
  },
  "kernel": {
    "axes": [
      {
        "id": "AX01",
        "key": "legal_domain",
        "values": [
          "constitutional_and_state_structure",
          "civil_and_contract",
          "company_and_corporate_governance",
          "securities_and_capital_markets",
          "banking_and_finance",
          "competition_and_antitrust",
          "consumer_protection",
          "intellectual_property",
          "data_and_cybersecurity",
          "labour_and_employment",
          "social_security",
          "environment_and_resource",
          "taxation",
          "administrative_law_and_procedure",
          "criminal_law_and_procedure",
          "procedural_law_civil",
          "procedural_law_administrative",
          "procedural_law_criminal",
          "foreign_investment_and_trade",
          "maritime_and_transport",
          "family_and_inheritance"
        ]
      },
      {
        "id": "AX02",
        "key": "instrument_type",
        "values": [
          "constitution_and_basic_law",
          "national_statute",
          "national_standing_committee_interpretation",
          "administrative_regulation_state_council",
          "judicial_interpretation_supreme_court",
          "judicial_interpretation_supreme_procuratorate",
          "local_regulation_provincial",
          "local_regulation_municipal",
          "departmental_rule_ministry_commission",
          "normative_document_guidance",
          "treaty_and_international_agreement",
          "judicial_guiding_case",
          "arbitration_rule"
        ]
      },
      {
        "id": "AX03",
        "key": "jurisdiction_level",
        "values": [
          "national",
          "provincial",
          "subprovincial_city",
          "county_or_district",
          "special_zone"
        ]
      },
      {
        "id": "AX04",
        "key": "forum_type",
        "values": [
          "supreme_court",
          "high_court",
          "intermediate_court",
          "basic_court",
          "specialized_court",
          "arbitration_commission",
          "administrative_agency",
          "tax_authority",
          "market_regulator",
          "competition_authority",
          "data_cyber_regulator",
          "environment_regulator",
          "labour_dispute_body"
        ]
      },
      {
        "id": "AX05",
        "key": "proceeding_type",
        "values": [
          "substantive_rule_interpretation",
          "legislative_drafting",
          "consultation_and_comment",
          "administrative_licensing",
          "administrative_enforcement",
          "administrative_penalty",
          "civil_dispute_resolution",
          "commercial_dispute_resolution",
          "labour_dispute_resolution",
          "tax_assessment_and_dispute",
          "criminal_investigation",
          "criminal_trial",
          "appeal_or_retrial",
          "arbitration_proceeding",
          "mediation"
        ]
      },
      {
        "id": "AX06",
        "key": "party_type",
        "values": [
          "state_body",
          "state_owned_enterprise",
          "private_company_domestic",
          "foreign_invested_enterprise",
          "financial_institution",
          "platform_company",
          "small_and_micro_enterprise",
          "individual_citizen",
          "foreign_individual_or_entity"
        ]
      },
      {
        "id": "AX07",
        "key": "time_horizon",
        "values": [
          "ex_ante_structuring",
          "ongoing_compliance",
          "incident_response",
          "enforcement_stage",
          "post_enforcement_rectification",
          "long_term_law_or_policy_change"
        ]
      },
      {
        "id": "AX08",
        "key": "risk_severity",
        "values": [
          "low_compliance_risk",
          "medium_compliance_risk",
          "high_compliance_risk",
          "administrative_high_risk",
          "criminal_exposure"
        ]
      },
      {
        "id": "AX09",
        "key": "cross_border_dimension",
        "values": [
          "purely_domestic",
          "foreign_investment_entry",
          "cross_border_trade_goods",
          "cross_border_trade_services",
          "data_cross_border_flow",
          "overseas_listing_or_financing",
          "sanctions_and_export_control_related"
        ]
      },
      {
        "id": "AX10",
        "key": "digitalisation_level",
        "values": [
          "paper_based",
          "mixed_analog_digital",
          "fully_digital",
          "platform_based_procedures"
        ]
      },
      {
        "id": "AX11",
        "key": "policy_priority",
        "values": [
          "policy_neutral",
          "policy_encouraged",
          "policy_restricted",
          "policy_phase_out"
        ]
      },
      {
        "id": "AX12",
        "key": "interpretive_source",
        "values": [
          "statutory_text_only",
          "statute_plus_judicial_interpretation",
          "statute_plus_admin_guidance",
          "statute_plus_local_regulation",
          "statute_plus_guiding_cases",
          "mixed_multi_source"
        ]
      }
    ],
    "dimensions_32": [
      {
        "id": "D01",
        "name": "Norm_Hierarchy_Clarity",
        "description": "Clarity of hierarchy between Constitution, statutes, regulations, rules, and interpretations."
      },
      {
        "id": "D02",
        "name": "Rule_Clarity_and_Specificity",
        "description": "How clearly the rules define rights, obligations, and prohibitions."
      },
      {
        "id": "D03",
        "name": "Interpretation_Availability",
        "description": "Availability of judicial interpretations, guidance, and precedents for the issue."
      },
      {
        "id": "D04",
        "name": "Local_Uniformity",
        "description": "Degree of uniform application across provinces and localities."
      },
      {
        "id": "D05",
        "name": "Enforcement_Predictability",
        "description": "Consistency and predictability of enforcement outcomes."
      },
      {
        "id": "D06",
        "name": "Enforcement_Intensity",
        "description": "Typical severity and frequency of enforcement in the domain."
      },
      {
        "id": "D07",
        "name": "Procedural_Transparency",
        "description": "Visibility of procedures, criteria, and decision-making processes."
      },
      {
        "id": "D08",
        "name": "Procedural_Safeguards",
        "description": "Availability of hearing, defence, representation, and appeal safeguards."
      },
      {
        "id": "D09",
        "name": "Evidence_Standards_Clarity",
        "description": "Clarity of evidence rules and standards for decision-making."
      },
      {
        "id": "D10",
        "name": "Remedies_and_Sanctions_Clarity",
        "description": "Definition of available remedies and sanctions and their ranges."
      },
      {
        "id": "D11",
        "name": "Institutional_Capacity",
        "description": "Capacity and expertise of the relevant courts or agencies."
      },
      {
        "id": "D12",
        "name": "Case_Handling_Timeliness",
        "description": "Typical timeframes for handling cases or procedures."
      },
      {
        "id": "D13",
        "name": "Compliance_Burden",
        "description": "Complexity and cost of implementing required controls and documentation."
      },
      {
        "id": "D14",
        "name": "Cross_Border_Compatibility",
        "description": "Compatibility with foreign legal expectations and treaties (where relevant)."
      },
      {
        "id": "D15",
        "name": "Sector_Specificity",
        "description": "Degree to which sector-specific rules refine or complicate the baseline regime."
      },
      {
        "id": "D16",
        "name": "Regulatory_Overlap",
        "description": "Extent of overlapping jurisdiction between agencies and legal regimes."
      },
      {
        "id": "D17",
        "name": "Dispute_Resolution_Options",
        "description": "Availability of courts, arbitration, mediation, and administrative reconsideration."
      },
      {
        "id": "D18",
        "name": "Predictability_of_Remedies",
        "description": "Predictability of compensation, penalties, or other remedies."
      },
      {
        "id": "D19",
        "name": "Documentation_and_Record_Requirements",
        "description": "Breadth and depth of record-keeping required for compliance and defence."
      },
      {
        "id": "D20",
        "name": "Policy_Change_Frequency",
        "description": "How frequently legal rules and policies in the domain change."
      },
      {
        "id": "D21",
        "name": "Policy_Alignment",
        "description": "Alignment with overarching policy goals and development plans."
      },
      {
        "id": "D22",
        "name": "Risk_Concentration",
        "description": "Concentration of risk in specific actors or transactions."
      },
      {
        "id": "D23",
        "name": "Human_Impact_and_Right_Sensitivity",
        "description": "Impact on personal rights, livelihoods, and social stability."
      },
      {
        "id": "D24",
        "name": "Economic_Impact_Significance",
        "description": "Scale of potential economic impact of compliance failure or enforcement."
      },
      {
        "id": "D25",
        "name": "Digital_and_Platform_Interaction",
        "description": "Involvement of digital platforms, e-courts, or online enforcement systems."
      },
      {
        "id": "D26",
        "name": "Evidence_and_Precedent_Strength",
        "description": "Depth of available cases, guiding cases, and interpretations in the domain."
      },
      {
        "id": "D27",
        "name": "Implementation_Readiness",
        "description": "Clarity of practical steps to meet legal and regulatory requirements."
      },
      {
        "id": "D28",
        "name": "Internal_Control_Requirement",
        "description": "Strength and complexity of internal control and compliance system requirements."
      },
      {
        "id": "D29",
        "name": "Third_Party_and_Ecosystem_Dependence",
        "description": "Dependence on third-party service providers or ecosystem partners to comply."
      },
      {
        "id": "D30",
        "name": "Systemic_Risk_Contribution",
        "description": "Potential for failure in the domain to create broader systemic or sectoral risk."
      },
      {
        "id": "D31",
        "name": "International_Scrutiny_Level",
        "description": "Extent of international focus, reporting, or scrutiny on the domain."
      },
      {
        "id": "D32",
        "name": "Overall_Legal_Risk_Level",
        "description": "Composite measure of legal and enforcement risk."
      }
    ],
    "tensor": {
      "structure": "axes[12] x dimensions[32]",
      "notes": "Any Chinese legal/regulatory question is represented as a tensor point defined by domain, instrument, jurisdiction, forum, proceeding type, party type, time horizon, risk level, cross-border aspects, digitalisation, policy priority, and interpretive sources."
    },
    "mapping_functions": {
      "F_normalize_legal_query": {
        "input": [
          "raw_query"
        ],
        "output": "CN_LAW_INPUT",
        "logic": "Extract domain(s), instrument focus, parties, forum, time horizon, risk level, and cross-border aspects from text."
      },
      "F_map_axes": {
        "input": [
          "CN_LAW_INPUT"
        ],
        "output": "axes_state",
        "logic": "Map CN_LAW_INPUT onto the 12 axes using explicit information and safe defaults where unspecified."
      },
      "F_dimension_profile": {
        "input": [
          "CN_LAW_INPUT",
          "axes_state"
        ],
        "output": "dimension_weights_32d",
        "logic": "Set an importance profile across the 32 dimensions (clarity, predictability, enforcement intensity, etc.)."
      },
      "F_stateframe": {
        "input": [
          "axes_state",
          "dimension_weights_32d"
        ],
        "output": "cn_law_stateframe",
        "logic": "Instantiate a kernel state used by downstream engine modes (mapping, risk evaluation, design)."
      }
    },
    "policies": {
      "safety": {
        "no_specific_legal_advice": true,
        "no_prediction_of_exact_case_outcomes": true,
        "always_recommend_licensed_counsel": true
      },
      "language": {
        "no_metaphor": true,
        "tone": "structural_clarity",
        "no_normative_judgment": true
      },
      "data": {
        "no_fabricated_statutes_or_cases": true,
        "must_flag_assumptions": true
      },
      "governance": {
        "anchor_to_MetaKernel_01": "Deterministic law, identity continuity, and boundary compliance apply.",
        "non_substitution_clause": "This kernel cannot substitute for up-to-date legal databases and professional analysis."
      }
    },
    "routing": {
      "by_objective": [
        {
          "pattern": "map_law|what_laws_apply|legal_framework",
          "mode": "cn_law_mapping"
        },
        {
          "pattern": "compliance|controls|policies|internal_rules",
          "mode": "cn_law_compliance_design"
        },
        {
          "pattern": "risk|exposure|liability|penalty",
          "mode": "cn_law_risk_evaluation"
        },
        {
          "pattern": "dispute|litigation|arbitration|appeal",
          "mode": "cn_law_dispute_pathways"
        },
        {
          "pattern": "reform|policy_option|legal_change|scenario",
          "mode": "cn_law_reform_options"
        }
      ]
    }
  },
  "engine": {
    "modes": {
      "cn_law_mapping": {
        "description": "High-level mapping of relevant legal domains, instruments, forums, and interpretive sources for a scenario.",
        "pipeline": [
          "F_normalize_legal_query",
          "F_map_axes",
          "F_dimension_profile",
          "F_stateframe",
          "CN_LAW_applicable_domain_map",
          "CN_LAW_instrument_and_forum_overview"
        ]
      },
      "cn_law_compliance_design": {
        "description": "Design of internal compliance structures, policies, and controls aligned with identified legal obligations.",
        "pipeline": [
          "F_normalize_legal_query",
          "F_map_axes",
          "F_dimension_profile",
          "F_stateframe",
          "CN_LAW_obligation_and_control_matrix",
          "CN_LAW_compliance_system_blueprint"
        ]
      },
      "cn_law_risk_evaluation": {
        "description": "Evaluation of legal and regulatory risk based on domain, enforcement patterns, and party characteristics.",
        "pipeline": [
          "F_normalize_legal_query",
          "F_map_axes",
          "F_dimension_profile",
          "F_stateframe",
          "CN_LAW_dimension_risk_scorecard",
          "CN_LAW_risk_heatmap",
          "CN_LAW_mitigation_option_outline"
        ]
      },
      "cn_law_dispute_pathways": {
        "description": "Mapping of possible dispute resolution pathways (court, arbitration, admin reconsideration, mediation).",
        "pipeline": [
          "F_normalize_legal_query",
          "F_map_axes",
          "F_dimension_profile",
          "F_stateframe",
          "CN_LAW_forum_and_pathway_options",
          "CN_LAW_pros_and_cons_matrix"
        ]
      },
      "cn_law_reform_options": {
        "description": "Scenario and reform options at the level of legal design or policy adjustment (conceptual only).",
        "pipeline": [
          "F_normalize_legal_query",
          "F_map_axes",
          "F_dimension_profile",
          "F_stateframe",
          "CN_LAW_scenario_set",
          "CN_LAW_impact_and_risk_view",
          "CN_LAW_potential_reform_paths"
        ]
      }
    },
    "components": {
      "scorecards": [
        "dimension_scorecard_0_100",
        "axis_profile",
        "legal_risk_heatmap"
      ],
      "artefact_templates": {
        "docs": [
          "cn_law_framework_mapping_memo",
          "cn_law_compliance_design_memo",
          "cn_law_risk_assessment_report",
          "cn_law_dispute_pathway_brief",
          "cn_law_reform_and_scenario_note"
        ],
        "decks": [
          "exec_cn_law_risk_overview",
          "board_cn_law_compliance_update",
          "cn_law_structural_change_deck"
        ],
        "tables": [
          "cn_law_obligation_control_matrix",
          "cn_law_domain_instrument_forum_table",
          "cn_law_dispute_pathway_comparison_matrix"
        ]
      }
    },
    "integration_links": {
      "kernel_level": [
        "kernel.axes",
        "kernel.dimensions_32",
        "kernel.tensor",
        "kernel.mapping_functions",
        "kernel.policies",
        "kernel.routing"
      ],
      "engine_level_refs": [
        "Policy_Geostrategy_Kernel_vInfinity_SUPER",
        "Risk_Compliance_Kernel_vInfinity_SUPER",
        "BizFin_Kernel_vInfinity"
      ],
      "notes": [
        "Provides a structural Chinese law/regulation lens for policy, risk, and business kernels.",
        "Must be used with live legal databases and qualified counsel for any real-world application."
      ]
    }
  },
  "benchmarks": {
    "global_reference_frameworks": [
      "Comparative civil-law codification structures (conceptual reference to hierarchy and domains).",
      "Rule-of-law and legal system assessment indices (conceptual metrics for clarity, predictability, and enforcement).",
      "Global corporate compliance frameworks covering multi-domain legal obligations (conceptual structures)."
    ],
    "coverage_matrix": {
      "legal_domain_coverage": {
        "target": "global_best_conceptual",
        "coverage_vs_target": 1.0,
        "notes": "Includes all major Chinese legal domains at structural level; does not embed statute texts."
      },
      "instrument_and_hierarchy_structure": {
        "target": "global_best_conceptual",
        "coverage_vs_target": 1.0,
        "notes": "Models main instrument types and hierarchy conceptually; requires external sources for details."
      },
      "risk_and_compliance_structuring": {
        "target": "global_best_conceptual",
        "coverage_vs_target": 1.0,
        "notes": "Provides full mapping, compliance design, and risk evaluation structures across domains."
      }
    },
    "limitations": [
      "Does not provide legal advice or official interpretations.",
      "Does not contain real statute, regulation, case, or enforcement data.",
      "All practical use must be reviewed and validated by licensed legal professionals."
    ]
  },
  "expansion": {
    "virtual_layer_count": 100000,
    "axes": [
      "legal_domain",
      "instrument_type",
      "jurisdiction_level",
      "forum_type",
      "proceeding_type",
      "party_type",
      "time_horizon",
      "risk_severity",
      "cross_border_dimension",
      "digitalisation_level",
      "policy_priority",
      "interpretive_source",
      "mode"
    ],
    "notes": [
      "Any concrete scenario involving Chinese law and regulations can be instantiated as a point in this tensor.",
      "Kernel+engine composition ensures structural coverage of all legal domains while remaining conceptual and non-prescriptive."
    ]
  }
}
"overlooked_elements_scanner_layer": {
  "description": "Scans for structurally under-recognised incentives and constraints by cross-checking program landscapes, sectors, and funding stacks.",
  "dimensions": [
    "underutilised_program_archetypes",
    "unusual_combinations_of_instruments",
    "hidden_administrative_constraints",
    "reporting_and_audit_burden_hotspots",
    "policy_gray_zones_and_ambiguities"
  ],
  "outputs": [
    "potentially_underused_structural_options",
    "high_friction_procedural_segments",
    "areas_requiring_professional_legal_or_tax_review"
  ],
  "must_not": [
    "design_or_recommend_evasion_schemes",
    "treat_gray_zones_as_exploitable_loopholes",
    "present_structural_observations_as_legal_or_tax_advice"
  ]
}